unogenerator/__init__.py
unogenerator/can_import_uno.py
unogenerator/commons.py
unogenerator/demo.py
unogenerator/exceptions.py
unogenerator/helpers.py
unogenerator/images/Imagewithborder.png
unogenerator/images/crown.png
unogenerator/images/icons.jpg
unogenerator/images/unogenerator.png
unogenerator/locale/en/LC_MESSAGES/unogenerator.mo
unogenerator/locale/en.po
unogenerator/locale/es/LC_MESSAGES/unogenerator.mo
unogenerator/locale/es.po
unogenerator/locale/fr/LC_MESSAGES/unogenerator.mo
unogenerator/locale/fr.po
unogenerator/locale/ro/LC_MESSAGES/unogenerator.mo
unogenerator/locale/ro.po
unogenerator/locale/unogenerator.pot
unogenerator/monitor.py
unogenerator/poethepoet.py
unogenerator/templates/colored.ods
unogenerator/templates/standard.ods
unogenerator/templates/standard.odt
unogenerator/translation.py
unogenerator/unogenerator.py
unogenerator-1.0.0.dist-info/LICENSE
unogenerator-1.0.0.dist-info/METADATA
unogenerator-1.0.0.dist-info/WHEEL
unogenerator-1.0.0.dist-info/entry_points.txt
unogenerator-1.0.0.dist-info/RECORD
