Metadata-Version: 2.1
Name: unogenerator
Version: 1.0.0
Summary: Libreoffice files generator programmatically with python and Libreoffice server instances
License: GPL-3.0 license
Author: turulomio
Author-email: turulomio@yahoo.es
Requires-Python: >3.9,<4
Classifier: License :: Other/Proprietary License
Classifier: Programming Language :: Python :: 3
Classifier: Programming Language :: Python :: 3.10
Classifier: Programming Language :: Python :: 3.11
Classifier: Programming Language :: Python :: 3.12
Requires-Dist: colorama (>=0.4.6)
Requires-Dist: humanize (>=4.11.0)
Requires-Dist: polib (>=1.2.0)
Requires-Dist: psutil (>=6.0.0)
Requires-Dist: pydicts (>=0.16.0)
Requires-Dist: tqdm (>=4.66.5)
